<?xml version="1.0"?>
<col:collection xmlns="http://cnx.rice.edu/collxml" xmlns:col="http://cnx.rice.edu/collxml" xml:lang="en" type="Manual" authors="Bridget Nash">
  <metadata xmlns:md="http://cnx.rice.edu/mdml" mdml-version="0.5">
    <md:content-id>col11342</md:content-id>
    <md:title>Physical Science Grade 10 Teachers' Guide - Siyavula WebBook</md:title>
    <md:license url="http://creativecommons.org/licenses/by/3.0/">Creative Commons Attribution License 3.0</md:license>
    <md:language>en</md:language>
    <md:uuid>d86b6d14-a1a3-483a-8b44-317fc9425a76</md:uuid>
    <md:slug>physical-science-grade-10-teachers-guide-siyavula-webbook</md:slug>
  </metadata>
  <col:content>
    <col:module document="m40362"/>
    <col:module document="m40364"/>
    <col:module document="m40363"/>
    <col:module document="m40367"/>
    <col:module document="m40353"/>
    <col:module document="m40356"/>
    <col:module document="m40357"/>
  </col:content>
</col:collection>
